tensorfloe/__init__.py
tensorfloe/chatbot.py
tensorfloe/gender.py
tensorfloe/latent.py
tensorfloe/pos.py
tensorfloe/sentiment.py
tensorfloe/skipgram.py
tensorfloe/spam.py
tensorfloe/summary.py
tensorfloe/transformer.py
tensorfloe/word2vec.py
axtriaalator-1.0.dist-info/METADATA
axtriaalator-1.0.dist-info/WHEEL
axtriaalator-1.0.dist-info/entry_points.txt
axtriaalator-1.0.dist-info/top_level.txt
axtriaalator-1.0.dist-info/RECORD
